Workbook

Sheet Cover
A1: APPLE INC.
A2: Financial Statement Analysis
A4: Prepared by:
A5: Lakshmi Nivas Mittal
A7: BBA
A8: Mohan Babu University
A10: Project 1
A11: Investment Banking Portfolio
A13: Date:
A14: 46235

Sheet Income Statement
A1: Particulars | B1: 2025 | C1: 2024 | D1: 2023 | E1: 2,022
A2: Product Revenue | B2: 307003 | C2: 294866 | D2: 298085 | E2: $316,199
A3: Service Revenue | B3: 109158 | C3: 96169 | D3: 85200 | E3: $78,129
A4: Total Revenue | B4: 416161 | C4: 391035 | D4: 383285 | E4: $394,328
A5: Product Cost | B5: 194116 | C5: 185233 | D5: 189282 | E5: $201,471
A6: Service Cost | B6: 26844 | C6: 25119 | D6: 24855 | E6: $22,075
A7: Total Cost | B7: 220960 | C7: 210352 | D7: 214137 | E7: $223,546
A8: Gross Margin | B8: 195201 | C8: 180683 | D8: 169148 | E8: $170,782
A9: R&D | B9: 34550 | C9: 31370 | D9: 29915 | E9: $26,251
A10: SG&A | B10: 27601 | C10: 26097 | D10: 24932 | E10: $25,094
A11: Total Operating Expenses | B11: 62151 | C11: 57467 | D11: 54847 | E11: $51,345
A12: Operating Income | B12: 133050 | C12: 123216 | D12: 114301 | E12: $119,437
A13: Other Income | B13: -321 | C13: 269 | D13: -565 | E13: -$334
... A16: Net Income | B16: 112010 | C16: 93736 | D16: 96995 | E16: $99,803

Sheet Balance Sheet
A1: Particulars | B1: 2025 | C1: 2024 | D1: 2023
A2: Cash | B2: 35934 | C2: 29943 | D2: 29965
A3: Marketable Securities | B3: 18763 | C3: 35228 | D3: 31590
A4: Accounts Receivable | B4: 39777 | C4: 33410 | D4: 29508
A5: Inventory | B5: 5718 | C5: 7286 | D5: 6331
A6: Total Current Assets | B6: 147957 | C6: 152987 | D6: 143566
A7: Total Non Current Assets | B7: 211284 | C7: 211993 | D7: 209017
A8: Total Assets | B8: 359241 | C8: 364980 | D8: 352583
A9: Total Current Liabilities | B9: 165631 | C9: 176392 | D9: 145308
A10: Total Non Current Liabilities | B10: 119877 | C10: 131638 | D10: 145129
A11: Total Liabilities | B11: 285508 | C11: 308030 | D11: 290437
A12: Shareholders' Equity | B12: 73733 | C12: 56950 | D12: 62146

Sheet Cash Flow Statement
A1: Particulars | B1: 2025 | C1: 2024 | D1: 2023
A2: Operating Cash Flow | B2: 111482 | C2: 118254 | D2: 110543
A3: Investing Cash Flow | B3: 15195 | C3: 2935 | D3: 3705
A4: Financing Cash Flow | B4: -120686 | C4: -121983 | D4: -108488
A5: Net Change in Cash | B5: 5991 | C5: -794 | D5: 5760
A6: Ending Cash | B6: 35934 | C6: 29943 | D6: 30737

Sheet Horizontal Analysis
A1: Particulars | B1: 2025 | C1: 2024 | D1: Change | E1: % Change
A2: Total Revenue | B2: ='Income Statement'!B4 -> 416161 | C2: ='Income Statement'!C4 -> 391035 | D2: =B2-C2 -> 25126 | E2: =(B2-C2)/C2 -> 0.064255118
A3: Gross Margin | B3: ='Income Statement'!B8 -> 195201 | C3: ='Income Statement'!C8 -> 180683 | D3: =B3-C3 -> 14518 | E3: =(B3-C3)/C3 -> 0.080350669
A4: Operating Income | B4: ='Income Statement'!B12 -> 133050 | C4: ='Income Statement'!C12 -> 123216 | D4: =B4-C4 -> 9834 | E4: =(B4-C4)/C4 -> 0.079811063
A5: Net Income | B5: ='Income Statement'!B16 -> 112010 | C5: ='Income Statement'!C16 -> 93736 | D5: =B5-C5 -> 18274 | E5: =(B5-C5)/C5 -> 0.19495178
A6: Total Assets | B6: ='Balance Sheet'!B8 -> 359241 | C6: ='Balance Sheet'!C8 -> 364980 | D6: =B6-C6 -> -5739 | E6: =(B6-C6)/C6 -> -0.015724149
A7: Total Liabilities | B7: ='Balance Sheet'!B11 -> 285508 | C7: ='Balance Sheet'!C11 -> 308030 | D7: =B7-C7 -> -22522 | E7: =(B7-C7)/C7 -> -0.073116255
A8: Operating Cash Flow | B8: ='Cash Flow Statement'!B2 -> 111482 | C8: ='Cash Flow Statement'!C2 -> 118254 | D8: =B8-C8 -> -6772 | E8: =(B8-C8)/C8 -> -0.057266562

Sheet Vertical Analysis
A1: Particulars | B1: 2025 | C1: 2024 | D1: 2023 | E1: 2025 % of Revenue | F1: 2024 % of Revenue | G1: 2023 % of Revenue
A2: Product Revenue | B2: =Table3[[#This Row],[2025]] -> 307003 | C2: =Table3[[#This Row],[2024]] -> 294866 | D2: =Table3[[#This Row],[2023]] -> 298085 | E2: =B2/B4 -> 0.73770248 | F2: =C2/C4 -> 0.75406549 | G2: =D2/D4 -> 0.7777111
A3: Service Revenue | B3: =Table3[[#This Row],[2025]] -> 109158 | C3: =Table3[[#This Row],[2024]] -> 96169 | D3: =Table3[[#This Row],[2023]] -> 85200 | E3: =B3/B4 -> 0.26229752 | F3: =C3/C4 -> 0.24593451 | G3: =D3/D4 -> 0.2222889
A4: Total Revenue | B4: =Table3[[#This Row],[2025]] -> 416161 | C4: =Table3[[#This Row],[2024]] -> 391035 | D4: =Table3[[#This Row],[2023]] -> 383285 | E4: =B4/B4 -> 1 | F4: =C4/C4 -> 1 | G4: =D4/D4 -> 1
A5: Product Cost | B5: =Table3[[#This Row],[2025]] -> 194116 | C5: =Table3[[#This Row],[2024]] -> 185233 | D5: =Table3[[#This Row],[2023]] -> 189282 | E5: =B5/B4 -> 0.46644448 | F5: =C5/C4 -> 0.47369929 | G5: =D5/D4 -> 0.4938414
A6: Service Cost | B6: =Table3[[#This Row],[2025]] -> 26844 | C6: =Table3[[#This Row],[2024]] -> 25119 | D6: =Table3[[#This Row],[2023]] -> 24855 | E6: =B6/B4 -> 0.064503882 | F6: =C6/C4 -> 0.064237217 | G6: =D6/D4 -> 0.064847307
A7: Total Cost | B7: =Table3[[#This Row],[2025]] -> 220960 | C7: =Table3[[#This Row],[2024]] -> 210352 | D7: =Table3[[#This Row],[2023]] -> 214137 | E7: =B7/B4 -> 0.53094836 | F7: =C7/C4 -> 0.5379365 | G7: =D7/D4 -> 0.5586887
A8: Gross Margin | B8: =Table3[[#This Row],[2025]] -> 195201 | C8: =Table3[[#This Row],[2024]] -> 180683 | D8: =Table3[[#This Row],[2023]] -> 169148 | E8: =B8/B4 -> 0.46905164 | F8: =C8/C4 -> 0.4620635 | G8: =D8/D4 -> 0.4413113
A9: R&D | B9: =Table3[[#This Row],[2025]] -> 34550 | C9: =Table3[[#This Row],[2024]] -> 31370 | D9: =Table3[[#This Row],[2023]] -> 29915 | E9: =B9/B4 -> 0.083020754 | F9: =C9/C4 -> 0.080222998 | G9: =D9/D4 -> 0.078048971
A10: SG&A | B10: =Table3[[#This Row],[2025]] -> 27601 | C10: =Table3[[#This Row],[2024]] -> 26097 | D10: =Table3[[#This Row],[2023]] -> 24932 | E10: =B10/B4 -> 0.066322889 | F10: =C10/C4 -> 0.066738272 | G10: =D10/D4 -> 0.065048202
A11: Total Operating Expenses | B11: =Table3[[#This Row],[2025]] -> 62151 | C11: =Table3[[#This Row],[2024]] -> 57467 | D11: =Table3[[#This Row],[2023]] -> 54847 | E11: =B11/B4 -> 0.14934364 | F11: =C11/C4 -> 0.14696127 | G11: =D11/D4 -> 0.14309717
A12: Operating Income | B12: =Table3[[#This Row],[2025]] -> 133050 | C12: =Table3[[#This Row],[2024]] -> 123216 | D12: =Table3[[#This Row],[2023]] -> 114301 | E12: =B12/B4 -> 0.319708 | F12: =C12/C4 -> 0.31510223 | G12: =D12/D4 -> 0.29821412
A13: Other Income | B13: =Table3[[#This Row],[2025]] -> -321 | C13: =Table3[[#This Row],[2024]] -> 269 | D13: =Table3[[#This Row],[2023]] -> -565 | E13: =B13/B4 -> -0.00077133609 | F13: =C13/C4 -> 0.00068791796 | G13: =D13/D4 -> -0.0014740989
A14: Income Before Tax | B14: =Table3[[#This Row],[2025]] -> 132729 | C14: =Table3[[#This Row],[2024]] -> 123485 | D14: =Table3[[#This Row],[2023]] -> 113736 | E14: =B14/B4 -> 0.31893666 | F14: =C14/C4 -> 0.31579015 | G14: =D14/D4 -> 0.29674002
A15: Income Tax | B15: =Table3[[#This Row],[2025]] -> 20719 | C15: =Table3[[#This Row],[2024]] -> 29749 | D15: =Table3[[#This Row],[2023]] -> 16741 | E15: =B15/B4 -> 0.04978602 | F15: =C15/C4 -> 0.076077589 | G15: =D15/D4 -> 0.043677681
A16: Net Income | B16: =Table3[[#This Row],[2025]] -> 112010 | C16: =Table3[[#This Row],[2024]] -> 93736 | D16: =Table3[[#This Row],[2023]] -> 96995 | E16: =B16/B4 -> 0.26915064 | F16: =C16/C4 -> 0.23971256 | G16: =D16/D4 -> 0.25306234

Sheet Ratio Analysis
A1: Ratio | B1: 2025 | C1: 2024 | D1: 2023
A2: Gross Profit Margin | B2: ='Income Statement'!B8/'Income Statement'!B4 -> 0.46905164 | C2: ='Income Statement'!C8/'Income Statement'!C4 -> 0.4620635 | D2: ='Income Statement'!D8/'Income Statement'!D4 -> 0.4413113
A3: Operating Profit Margin | B3: ='Income Statement'!B12/'Income Statement'!B4 -> 0.319708 | C3: ='Income Statement'!C12/'Income Statement'!C4 -> 0.31510223 | D3: ='Income Statement'!D12/'Income Statement'!D4 -> 0.29821412
A4: Net Profit Margin | B4: ='Income Statement'!B16/'Income Statement'!B4 -> 0.26915064 | C4: ='Income Statement'!C16/'Income Statement'!C4 -> 0.23971256 | D4: ='Income Statement'!D16/'Income Statement'!D4 -> 0.25306234
A5: ROA | B5: ='Income Statement'!B16/AVERAGE('Balance Sheet'!B8,'Balance Sheet'!C8) -> 0.30932547 | C5: ='Income Statement'!C16/AVERAGE('Balance Sheet'!C8,'Balance Sheet'!D8) -> 0.26126208 | D5: ='Income Statement'!D16/'Balance Sheet'!D8 -> 0.27509835
A6: ROE | B6: ='Income Statement'!B16/AVERAGE('Balance Sheet'!B12,'Balance Sheet'!C12) -> 1.7142245 | C6: ='Income Statement'!C16/AVERAGE('Balance Sheet'!C12,'Balance Sheet'!D12) -> 1.5741251 | D6: ='Income Statement'!D16/'Balance Sheet'!D12 -> 1.5607601

Sheet Dashboard
A1: APPLE INC.-- FINANCIAL ANALYSIS DASHBOARD
A3: Revenue | C3: Gross Margin | E3: Operating Income | G3: Net Income | I3: Net Profit Margin
A4: ='Income Statement'!B4 -> 416161 | C4: ='Income Statement'!B8 -> 195201 | E4: ='Income Statement'!B12 -> 133050 | G4: ='Income Statement'!B16 -> 112010 | I4: ='Ratio Analysis'!B4 -> 0.26915064
A8: Metric | B8: 2023 | C8: 2024 | D8: 2025 | F8: Margin | G8: 2023 | H8: 2024 | I8: 2025
A9: Revenue | B9: ='Income Statement'!D4 -> 383285 | C9: ='Income Statement'!C4 -> 391035 | D9: ='Income Statement'!B4 -> 416161 | F9: Gross Profit Margin | G9: ='Ratio Analysis'!D2 -> 0.4413113 | H9: ='Ratio Analysis'!C2 -> 0.4620635 | I9: ='Ratio Analysis'!B2 -> 0.46905164
A10: Gross Margin | B10: ='Income Statement'!D8 -> 169148 | C10: ='Income Statement'!C8 -> 180683 | D10: ='Income Statement'!B8 -> 195201 | F10: Operating Profit Margin | G10: ='Ratio Analysis'!D3 -> 0.29821412 | H10: ='Ratio Analysis'!C3 -> 0.31510223 | I10: ='Ratio Analysis'!B3 -> 0.319708
A11: Operating Income | B11: ='Income Statement'!D12 -> 114301 | C11: ='Income Statement'!C12 -> 123216 | D11: ='Income Statement'!B12 -> 133050 | F11: Net Profit Margin | G11: ='Ratio Analysis'!D4 -> 0.25306234 | H11: ='Ratio Analysis'!C4 -> 0.23971256 | I11: ='Ratio Analysis'!B4 -> 0.26915064
A12: Net Income | B12: ='Income Statement'!D16 -> 96995 | C12: ='Income Statement'!C16 -> 93736 | D12: ='Income Statement'!B16 -> 112010
A15: Financial Position | B15: 2023 | C15: 2024 | D15: 2025
A16: Total Assets | B16: ='Balance Sheet'!D8 -> 352583 | C16: ='Balance Sheet'!C8 -> 364980 | D16: ='Balance Sheet'!B8 -> 359241
A17: Total Liabilities | B17: ='Balance Sheet'!D11 -> 290437 | C17: ='Balance Sheet'!C11 -> 308030 | D17: ='Balance Sheet'!B11 -> 285508

Sheet Insights
A1: APPLE INC. — FINANCIAL ANALYSIS INSIGHTS
A2: Area | B2: Analyst Insight
A3: Revenue Growth | B3: Apple’s revenue increased from $383.3B in 2023 to $391.0B in 2024 and $416.2B in 2025. The strongest growth occurred in 2025, indicating improved top-line momentum.
A4: Profitability | B4: Gross profit margin improved from approximately 44.1% in 2023 to 46.9% in 2025. Operating profit margin also increased from approximately 29.8% to 32.0%, showing stronger operating efficiency.
A5: Net Income | B5: Net income declined slightly in 2024 but increased significantly in 2025 to approximately $112.0B. Net profit margin reached approximately 26.9% in 2025, demonstrating strong earnings performance.
A6: Financial Position | B6: Total assets decreased slightly from $365.0B in 2024 to $359.2B in 2025, while total liabilities declined from $308.0B to $285.5B. The reduction in liabilities indicates an improvement in the company’s overall balance-sheet position.
A7: Liquidity / Balance Sheet | B7: Current assets decreased moderately in 2025, while current liabilities also declined. This should be monitored alongside Apple’s cash, marketable securities and operating cash generation to assess short-term financial flexibility.
A8: Shareholder Returns | B8: ROE remains exceptionally high, reflecting Apple’s ability to generate substantial earnings relative to shareholders’ equity. However, the unusually high ROE should be interpreted in the context of Apple’s relatively low equity base.
A9: Overall Assessment | B9: Apple demonstrated strong financial performance in 2025, with accelerating revenue, higher profitability and substantially improved net income. Overall, the company shows strong earnings power and operating efficiency, while its balance-sheet structure and shareholder returns remain important areas for continued analysis.
